pncli/__init__.py
pncli/__main__.py
pncli/main.py
pncli-1.0.0.dist-info/METADATA
pncli-1.0.0.dist-info/WHEEL
pncli-1.0.0.dist-info/entry_points.txt
pncli-1.0.0.dist-info/RECORD
