Metadata-Version: 2.1
Name: pncli
Version: 1.0.0
Summary: 
Author: petnowbrian
Author-email: brian.cho@petnow.io
Requires-Python: >=3.8,<4.0
Classifier: Programming Language :: Python :: 3
Classifier: Programming Language :: Python :: 3.8
Classifier: Programming Language :: Python :: 3.9
Classifier: Programming Language :: Python :: 3.10
Classifier: Programming Language :: Python :: 3.11
Requires-Dist: typer (>=0.12.3,<0.13.0)
